panda3d_kivy/__init__.py
panda3d_kivy/app.py
panda3d_kivy/config.py
panda3d_kivy/monkey.py
panda3d_kivy/core/__init__.py
panda3d_kivy/core/window.py
render_pipeline/__init__.py
render_pipeline/setup.py
render_pipeline/start_daytime_editor.py
render_pipeline/start_plugin_configurator.py
render_pipeline/rpcore/__init__.py
render_pipeline/rpcore/common_resources.py
render_pipeline/rpcore/effect.py
render_pipeline/rpcore/globals.py
render_pipeline/rpcore/gpu_command_queue.py
render_pipeline/rpcore/image.py
render_pipeline/rpcore/light_manager.py
render_pipeline/rpcore/loader.py
render_pipeline/rpcore/mount_manager.py
render_pipeline/rpcore/render_pipeline.py
render_pipeline/rpcore/render_stage.py
render_pipeline/rpcore/render_target.py
render_pipeline/rpcore/rpobject.py
render_pipeline/rpcore/stage_manager.py
render_pipeline/rpcore/gui/__init__.py
render_pipeline/rpcore/gui/buffer_viewer.py
render_pipeline/rpcore/gui/checkbox.py
render_pipeline/rpcore/gui/checkbox_collection.py
render_pipeline/rpcore/gui/debugger.py
render_pipeline/rpcore/gui/draggable_window.py
render_pipeline/rpcore/gui/error_message_display.py
render_pipeline/rpcore/gui/exposure_widget.py
render_pipeline/rpcore/gui/fps_chart.py
render_pipeline/rpcore/gui/labeled_checkbox.py
render_pipeline/rpcore/gui/loading_screen.py
render_pipeline/rpcore/gui/pipe_viewer.py
render_pipeline/rpcore/gui/pixel_inspector.py
render_pipeline/rpcore/gui/render_mode_selector.py
render_pipeline/rpcore/gui/slider.py
render_pipeline/rpcore/gui/sprite.py
render_pipeline/rpcore/gui/text.py
render_pipeline/rpcore/gui/text_node.py
render_pipeline/rpcore/gui/texture_preview.py
render_pipeline/rpcore/native/__init__.py
render_pipeline/rpcore/native/update_module_builder.py
render_pipeline/rpcore/pluginbase/__init__.py
render_pipeline/rpcore/pluginbase/base_plugin.py
render_pipeline/rpcore/pluginbase/day_manager.py
render_pipeline/rpcore/pluginbase/day_setting_types.py
render_pipeline/rpcore/pluginbase/manager.py
panda3d_kivy-0.5.4.dist-info/LICENSE
panda3d_kivy-0.5.4.dist-info/METADATA
panda3d_kivy-0.5.4.dist-info/WHEEL
panda3d_kivy-0.5.4.dist-info/top_level.txt
panda3d_kivy-0.5.4.dist-info/RECORD
