Metadata-Version: 2.2
Name: panda3d-kivy
Version: 0.5.4
Summary: Panda3D add-on for Kivy integration.
Home-page: https://github.com/Cheaterman/panda3d-kivy
Author: Cheaterman
Author-email: the.cheaterman@gmail.com
License: MIT
Classifier: Programming Language :: Python :: 3
Classifier: License :: OSI Approved :: MIT License
Classifier: Operating System :: OS Independent
Requires-Python: >=3.6
License-File: LICENSE
Requires-Dist: panda3d
Requires-Dist: kivy
Dynamic: author
Dynamic: author-email
Dynamic: classifier
Dynamic: description
Dynamic: description-content-type
Dynamic: home-page
Dynamic: license
Dynamic: requires-dist
Dynamic: requires-python
Dynamic: summary
